aidge_benchmark/__init__.py
aidge_benchmark/benchmark_scheme.py
aidge_benchmark/format_descriptor.py
aidge_benchmark/model_inference.py
aidge_benchmark/operation_config.py
aidge_benchmark/tensor_specs.py
aidge_benchmark/operations_config/abs.json
aidge_benchmark/operations_config/add.json
aidge_benchmark/operations_config/and.json
aidge_benchmark/operations_config/argmax.json
aidge_benchmark/operations_config/atan.json
aidge_benchmark/operations_config/avgpooling2d.json
aidge_benchmark/operations_config/batchnorm2d.json
aidge_benchmark/operations_config/binary_broadcast.json
aidge_benchmark/operations_config/binary_elementwise.json
aidge_benchmark/operations_config/bitshift.json
aidge_benchmark/operations_config/ceil.json
aidge_benchmark/operations_config/clip.json
aidge_benchmark/operations_config/constant_of_shape.json
aidge_benchmark/operations_config/conv2d.json
aidge_benchmark/operations_config/conv_transpose2d.json
aidge_benchmark/operations_config/convdepthwise2d.json
aidge_benchmark/operations_config/cryptohash.json
aidge_benchmark/operations_config/div.json
aidge_benchmark/operations_config/equal.json
aidge_benchmark/operations_config/erf.json
aidge_benchmark/operations_config/exp.json
aidge_benchmark/operations_config/fc.json
aidge_benchmark/operations_config/features_padding.json
aidge_benchmark/operations_config/floor.json
aidge_benchmark/operations_config/global_average_pooling.json
aidge_benchmark/operations_config/hard_sigmoid.json
aidge_benchmark/operations_config/hardmax.json
aidge_benchmark/operations_config/heaviside.json
aidge_benchmark/operations_config/layer_normalization.json
aidge_benchmark/operations_config/leakyrelu.json
aidge_benchmark/operations_config/ln.json
aidge_benchmark/operations_config/lrn.json
aidge_benchmark/operations_config/many_broadcast.json
aidge_benchmark/operations_config/many_elementwise.json
aidge_benchmark/operations_config/matmul.json
aidge_benchmark/operations_config/max.json
aidge_benchmark-0.1.0.dist-info/licenses/LICENSE
aidge_benchmark-0.1.0.dist-info/METADATA
aidge_benchmark-0.1.0.dist-info/WHEEL
aidge_benchmark-0.1.0.dist-info/top_level.txt
aidge_benchmark-0.1.0.dist-info/RECORD
