Metadata-Version: 2.4
Name: aidge-benchmark
Version: 0.1.0
Summary: Benchmarking tool for Eclipse Aidge - validate model correctness, precision, and performance across multiple libraries.
License: Eclipse Public License - v 2.0
Project-URL: Homepage, https://www.deepgreen.ai/en/platform
Project-URL: Documentation, https://eclipse.dev/aidge/
Project-URL: Repository, https://gitlab.eclipse.org/eclipse/aidge/aidge_benchmark
Project-URL: Issues, https://gitlab.eclipse.org/eclipse/aidge/aidge_benchmark/-/issues/
Project-URL: Changelog, https://gitlab.eclipse.org/eclipse/aidge/aidge_benchmark/-/releases
Keywords: aidge,benchmark,inference time,performance,testing
Classifier: Development Status :: 2 - Pre-Alpha
Classifier: Programming Language :: Python :: 3
Classifier: Programming Language :: Python :: 3.10
Classifier: Programming Language :: Python :: 3.11
Classifier: Programming Language :: Python :: 3.12
Requires-Python: >=3.10
License-File: LICENSE
Requires-Dist: numpy>=1.22.0
Requires-Dist: aidge-core>=0.6.2
Provides-Extra: displaying
Requires-Dist: rich; extra == "displaying"
Requires-Dist: matplotlib; extra == "displaying"
Provides-Extra: external
Requires-Dist: onnx; extra == "external"
Requires-Dist: onnxruntime>=1.18; extra == "external"
Requires-Dist: torch; extra == "external"
Provides-Extra: test
Requires-Dist: pytest; extra == "test"
Dynamic: license-file
